README.md
pyproject.toml
fieldreporter/__init__.py
fieldreporter/__main__.py
fieldreporter/config.py
fieldreporter/exceptions.py
fieldreporter/logging.py
fieldreporter/reporter.py
fieldreporter.egg-info/PKG-INFO
fieldreporter.egg-info/SOURCES.txt
fieldreporter.egg-info/dependency_links.txt
fieldreporter.egg-info/requires.txt
fieldreporter.egg-info/top_level.txt
fieldreporter/conditions/__init__.py
fieldreporter/conditions/disk_space.py
fieldreporter/conditions/model.py
fieldreporter/conditions/paths_exist.py
fieldreporter/conditions/uptime.py
fieldreporter/destinations/__init__.py
fieldreporter/destinations/telegram.py