Metadata-Version: 2.4
Name: fieldreporter
Version: 0.0.5
Summary: Alerting and reporting issues on remote systems
Author-email: Daniel Jones <dan-code@erase.net>
License-Expression: MIT
Requires-Python: >=3.9
Requires-Dist: fieldreporter
Requires-Dist: apscheduler
Requires-Dist: pyyaml
